mccpdc_pk/__init__.py
mccpdc_pk/mccpdc.py
mccpdc_pk-0.1.1.dist-info/METADATA
mccpdc_pk-0.1.1.dist-info/WHEEL
mccpdc_pk-0.1.1.dist-info/entry_points.txt
mccpdc_pk-0.1.1.dist-info/RECORD
