Metadata-Version: 2.4
Name: mccpdc-pk
Version: 0.1.1
Summary: Add your description here
Author-email: mwine <mwine81@gmail.com>
Requires-Python: >=3.10
Requires-Dist: polars
